matrices_evolved/__init__.py
matrices_evolved/_event_signing_impl.cpython-313-aarch64-linux-gnu.so
matrices_evolved/cpp.py
matrices_evolved/matrices_evolved_rust.so
matrices_evolved/rust.py
matrices_evolved-1.0.10.dist-info/METADATA
matrices_evolved-1.0.10.dist-info/WHEEL
matrices_evolved-1.0.10.dist-info/RECORD
matrices_evolved-1.0.10.dist-info/licenses/LICENSE
