Metadata-Version: 2.1
Name: matrices-evolved
Version: 1.0.10
Summary: High-performance Matrix event signing library
Author-Email: Aless Microsystems <albertalesso@gmail.com>
License: Aless Microsystems Source‑Available License (Non‑Commercial, No Military, No Government) v1.0
Classifier: Development Status :: 4 - Beta
Classifier: Intended Audience :: Developers
Classifier: License :: Other/Proprietary License
Classifier: Programming Language :: Python :: 3
Classifier: Topic :: Security :: Cryptography
Requires-Python: >=3.8
Requires-Dist: nanobind>=2.0.0
